compare_frames_g4/__init__.py
compare_frames_g4-1.1.0.dist-info/LICENSE
compare_frames_g4-1.1.0.dist-info/METADATA
compare_frames_g4-1.1.0.dist-info/WHEEL
compare_frames_g4-1.1.0.dist-info/top_level.txt
compare_frames_g4-1.1.0.dist-info/RECORD
