Metadata-Version: 2.1
Name: compare-frames-g4
Version: 1.1.0
Summary: Compare 2 frames
Home-page: https://github.com/Genzo4/compare_frames
Author: Genzo
Author-email: genzo@bk.ru
License: MIT
Project-URL: Bug Tracker, https://github.com/Genzo4/compare_frames/issues
Keywords: g4,compare_frames,compare frames
Classifier: Development Status :: 5 - Production/Stable
Classifier: Programming Language :: Python :: 3
Classifier: Programming Language :: Python :: 3.6
Classifier: Programming Language :: Python :: 3.7
Classifier: Programming Language :: Python :: 3.8
Classifier: Programming Language :: Python :: 3.9
Classifier: Programming Language :: Python :: 3.10
Classifier: Programming Language :: Python :: 3.11
Classifier: License :: OSI Approved :: MIT License
Classifier: Operating System :: OS Independent
Classifier: Intended Audience :: Developers
Classifier: Natural Language :: English
Classifier: Natural Language :: Russian
Classifier: Topic :: Software Development
Classifier: Topic :: Software Development :: Libraries :: Python Modules
Classifier: Topic :: Utilities
Requires-Python: >=3.6
License-File: LICENSE
Requires-Dist: opencv-contrib-python <4.6
Requires-Dist: numpy
Requires-Dist: multipledispatch
